django_matthaios/__init__.py
django_matthaios/admin.py
django_matthaios/apps.py
django_matthaios/migrations/0001_initial.py
django_matthaios/migrations/__init__.py
django_matthaios/models/__init__.py
django_matthaios/models/other_models.py
django_matthaios/models/party_models.py
django_matthaios/models/transaction_models.py
django_matthaios/tests/__init__.py
django_matthaios/tests/party_tests.py
django_matthaios-0.1.1.dist-info/METADATA
django_matthaios-0.1.1.dist-info/WHEEL
django_matthaios-0.1.1.dist-info/RECORD
